youtube_dl_service/__init__.py
youtube_dl_service-0.0.2.dist-info/LICENCE
youtube_dl_service-0.0.2.dist-info/METADATA
youtube_dl_service-0.0.2.dist-info/WHEEL
youtube_dl_service-0.0.2.dist-info/top_level.txt
youtube_dl_service-0.0.2.dist-info/RECORD
