Metadata-Version: 2.1
Name: youtube-dl-service
Version: 0.0.2
Summary: Using youtube-dl as service in python code
Home-page: UNKNOWN
Author: Dmitriy Pleshevskiy
Author-email: dmitriy@ideascup.me
License: MIT
Platform: UNKNOWN
Requires-Dist: youtube-dl (==2020.12.29)
